MANIFEST.in
setup.cfg
setup.py
django_roxyfileman.egg-info/PKG-INFO
django_roxyfileman.egg-info/SOURCES.txt
django_roxyfileman.egg-info/dependency_links.txt
django_roxyfileman.egg-info/pbr.json
django_roxyfileman.egg-info/requires.txt
django_roxyfileman.egg-info/top_level.txt
roxyfileman/__init__.py
roxyfileman/settings.py
roxyfileman/urls.py
roxyfileman/utils.py
roxyfileman/views.py
roxyfileman/static/roxyfileman/css/jquery-ui-1.10.4.custom.css
roxyfileman/static/roxyfileman/css/jquery-ui-1.10.4.custom.min.css
roxyfileman/static/roxyfileman/css/main.css
roxyfileman/static/roxyfileman/css/main.min.css
roxyfileman/static/roxyfileman/css/images/animated-overlay.gif
roxyfileman/static/roxyfileman/css/images/ui-bg_flat_0_aaaaaa_40x100.png
roxyfileman/static/roxyfileman/css/images/ui-bg_flat_75_ffffff_40x100.png
roxyfileman/static/roxyfileman/css/images/ui-bg_glass_55_fbf9ee_1x400.png
roxyfileman/static/roxyfileman/css/images/ui-bg_glass_65_ffffff_1x400.png
roxyfileman/static/roxyfileman/css/images/ui-bg_glass_75_dadada_1x400.png
roxyfileman/static/roxyfileman/css/images/ui-bg_glass_75_e6e6e6_1x400.png
roxyfileman/static/roxyfileman/css/images/ui-bg_glass_95_fef1ec_1x400.png
roxyfileman/static/roxyfileman/css/images/ui-bg_highlight-soft_75_cccccc_1x100.png
roxyfileman/static/roxyfileman/css/images/ui-icons_222222_256x240.png
roxyfileman/static/roxyfileman/css/images/ui-icons_2e83ff_256x240.png
roxyfileman/static/roxyfileman/css/images/ui-icons_454545_256x240.png
roxyfileman/static/roxyfileman/css/images/ui-icons_888888_256x240.png
roxyfileman/static/roxyfileman/css/images/ui-icons_cd0a0a_256x240.png
roxyfileman/static/roxyfileman/images/action-folder-paste.png
roxyfileman/static/roxyfileman/images/action-folder-rename.png
roxyfileman/static/roxyfileman/images/arrow_down.png
roxyfileman/static/roxyfileman/images/arrow_up.png
roxyfileman/static/roxyfileman/images/blank.gif
roxyfileman/static/roxyfileman/images/copy.png
roxyfileman/static/roxyfileman/images/cut.png
roxyfileman/static/roxyfileman/images/dir-minus.png
roxyfileman/static/roxyfileman/images/dir-plus.png
roxyfileman/static/roxyfileman/images/file-add.png
roxyfileman/static/roxyfileman/images/file-delete.png
