Metadata-Version: 1.1
Name: django-roxyfileman
Version: 1.142.3
Summary: Integrate Django with Roxy Fileman
Home-page: https://github.com/zenwalker/django-roxyfileman
Author: Maxim Poletaev
Author-email: max.poletaev@gmail.com
License: GPLv3
Keywords: filemanager
Platform: UNKNOWN
Classifier: Programming Language :: Python :: 3
Classifier: Programming Language :: Python :: 3.3
Classifier: Programming Language :: Python :: 3.4
Classifier: Programming Language :: Python :: 3.5
Classifier: Framework :: Django :: 1.8
Classifier: Framework :: Django :: 1.9
